{
  "project_info": {
    "project_number": "1020493917646",
    "firebase_url": "https://trysub-7d847.firebaseio.com",
    "project_id": "trysub-7d847",
    "storage_bucket": "trysub-7d847.appspot.com"
  },
  "client": [
    {
      "client_info": {
        "mobilesdk_app_id": "1:1020493917646:android:9b6c830e28be4245",
        "android_client_info": {
          "package_name": "com.egco428.trysub"
        }
      },
      "oauth_client": [
        {
          "client_id": "1020493917646-knlcu373iekoiajjkntu731fi5qu96bj.apps.googleusercontent.com",
          "client_type": 1,
          "android_info": {
            "package_name": "com.egco428.trysub",
            "certificate_hash": "634c1608aa12035738f910e929cd6abc24f10a8c"
          }
        },
        {
          "client_id": "1020493917646-ea9n64joj8b8brouf7i2g5t27li3o3aj.apps.googleusercontent.com",
          "client_type": 1,
          "android_info": {
            "package_name": "com.egco428.trysub",
            "certificate_hash": "5e9651ea06e92b2a456af659baa2ed0793775f97"
          }
        },
        {
          "client_id": "1020493917646-rn39i5p02oka1icln3crn3ld76l7f8sr.apps.googleusercontent.com",
          "client_type": 1,
          "android_info": {
            "package_name": "com.egco428.trysub",
            "certificate_hash": "5403c0241d00b5493eea372053a22e23986345bc"
          }
        },
        {
          "client_id": "1020493917646-1a7rhe79taab6u5g5lj9qdo4fck42d18.apps.googleusercontent.com",
          "client_type": 3
        }
      ],
      "api_key": [
        {
          "current_key": "AIzaSyC9eUEmYhd1yrgFR1m79uSMMz69Wh0r6Q8"
        }
      ],
      "services": {
        "analytics_service": {
          "status": 1
        },
        "appinvite_service": {
          "status": 2,
          "other_platform_oauth_client": [
            {
              "client_id": "1020493917646-1a7rhe79taab6u5g5lj9qdo4fck42d18.apps.googleusercontent.com",
              "client_type": 3
            }
          ]
        },
        "ads_service": {
          "status": 2
        }
      }
    }
  ],
  "configuration_version": "1"
}